flea/__init__.py
flea/agent.py
flea/exceptions.py
flea/html.py
flea/util.py
flea/wsgi.py
flea-9.1.1.dist-info/LICENCE.TXT
flea-9.1.1.dist-info/METADATA
flea-9.1.1.dist-info/WHEEL
flea-9.1.1.dist-info/top_level.txt
flea-9.1.1.dist-info/RECORD
