Metadata-Version: 2.1
Name: flea
Version: 9.1.1
Summary: Functional testing for WSGI: drive WSGI apps from your test suite
Home-page: https://ollycope.com/software/flea/latest/
Author: Oliver Cope
Author-email: oliver@redgecko.org
License: Apache
Keywords: wsgi,tests,testing,pytest,nose
Classifier: Development Status :: 4 - Beta
Classifier: Environment :: Web Environment
Classifier: Intended Audience :: Developers
Classifier: License :: OSI Approved :: Apache Software License
Classifier: Operating System :: OS Independent
Classifier: Topic :: Internet :: WWW/HTTP :: WSGI
Classifier: Topic :: Software Development :: Testing
Classifier: Programming Language :: Python :: 3
License-File: LICENCE.TXT
Requires-Dist: fresco (>=2.0.0)
Requires-Dist: lxml
Requires-Dist: cssselect
